pyaview/__init__.py
pyaview-0.0.1.data/scripts/pyaview
pyaview-0.0.1.dist-info/METADATA
pyaview-0.0.1.dist-info/WHEEL
pyaview-0.0.1.dist-info/top_level.txt
pyaview-0.0.1.dist-info/RECORD
