Metadata-Version: 2.1
Name: pyaview
Version: 0.0.1
Summary: A modern python alternative of the ls binary!
Home-page: UNKNOWN
Author: Birdlinux (G. P.)
Author-email: <prepakis.geo@gmail.com>
License: UNKNOWN
Keywords: python ls,python system Detection,python hex,python rgb,python hex,python loader,rich python,python rich,cutepy
Platform: UNKNOWN
